ipaplatform/__init__.py
ipaplatform/_importhook.py
ipaplatform/constants.py
ipaplatform/osinfo.py
ipaplatform/paths.py
ipaplatform/services.py
ipaplatform/tasks.py
ipaplatform/base/__init__.py
ipaplatform/base/constants.py
ipaplatform/base/paths.py
ipaplatform/base/services.py
ipaplatform/base/tasks.py
ipaplatform/debian/__init__.py
ipaplatform/debian/constants.py
ipaplatform/debian/paths.py
ipaplatform/debian/services.py
ipaplatform/debian/tasks.py
ipaplatform/fedora/__init__.py
ipaplatform/fedora/constants.py
ipaplatform/fedora/paths.py
ipaplatform/fedora/services.py
ipaplatform/fedora/tasks.py
ipaplatform/fedora_container/__init__.py
ipaplatform/fedora_container/constants.py
ipaplatform/fedora_container/paths.py
ipaplatform/fedora_container/services.py
ipaplatform/fedora_container/tasks.py
ipaplatform/nixos/__init__.py
ipaplatform/nixos/constants.py
ipaplatform/nixos/paths.py
ipaplatform/nixos/services.py
ipaplatform/nixos/tasks.py
ipaplatform/opencloudos/__init__.py
ipaplatform/opencloudos/constants.py
ipaplatform/opencloudos/paths.py
ipaplatform/opencloudos/services.py
ipaplatform/opencloudos/tasks.py
ipaplatform/redhat/__init__.py
ipaplatform/redhat/authconfig.py
ipaplatform/redhat/constants.py
ipaplatform/redhat/paths.py
ipaplatform/redhat/services.py
ipaplatform/redhat/tasks.py
ipaplatform/rhel/__init__.py
ipaplatform/rhel/constants.py
ipaplatform/rhel/paths.py
ipaplatform/rhel/services.py
ipaplatform/rhel/tasks.py
ipaplatform/rhel_container/__init__.py
ipaplatform/rhel_container/constants.py
ipaplatform/rhel_container/paths.py
ipaplatform/rhel_container/services.py
ipaplatform/rhel_container/tasks.py
ipaplatform/suse/__init__.py
ipaplatform/suse/constants.py
ipaplatform/suse/paths.py
ipaplatform/suse/services.py
ipaplatform/suse/tasks.py
ipaplatform/tencentos/__init__.py
ipaplatform/tencentos/constants.py
ipaplatform/tencentos/paths.py
ipaplatform/tencentos/services.py
ipaplatform/tencentos/tasks.py
ipaplatform-4.12.2.dist-info/COPYING
ipaplatform-4.12.2.dist-info/METADATA
ipaplatform-4.12.2.dist-info/WHEEL
ipaplatform-4.12.2.dist-info/top_level.txt
ipaplatform-4.12.2.dist-info/RECORD
